setup.py
CsuPTMD.egg-info/PKG-INFO
CsuPTMD.egg-info/SOURCES.txt
CsuPTMD.egg-info/dependency_links.txt
CsuPTMD.egg-info/requires.txt
CsuPTMD.egg-info/top_level.txt
PTMD/__init__.py
PTMD/model.py
PTMD/maskrcnn_benchmark/__init__.py
PTMD/maskrcnn_benchmark/apex/__init__.py
PTMD/maskrcnn_benchmark/apex/setup.py
PTMD/maskrcnn_benchmark/apex/apex/__init__.py
PTMD/maskrcnn_benchmark/apex/apex/RNN/RNNBackend.py
PTMD/maskrcnn_benchmark/apex/apex/RNN/__init__.py
PTMD/maskrcnn_benchmark/apex/apex/RNN/cells.py
PTMD/maskrcnn_benchmark/apex/apex/RNN/models.py
PTMD/maskrcnn_benchmark/apex/apex/amp/__init__.py
PTMD/maskrcnn_benchmark/apex/apex/amp/__version__.py
PTMD/maskrcnn_benchmark/apex/apex/amp/_amp_state.py
PTMD/maskrcnn_benchmark/apex/apex/amp/_initialize.py
PTMD/maskrcnn_benchmark/apex/apex/amp/_process_optimizer.py
PTMD/maskrcnn_benchmark/apex/apex/amp/amp.py
PTMD/maskrcnn_benchmark/apex/apex/amp/compat.py
PTMD/maskrcnn_benchmark/apex/apex/amp/frontend.py
PTMD/maskrcnn_benchmark/apex/apex/amp/handle.py
PTMD/maskrcnn_benchmark/apex/apex/amp/opt.py
PTMD/maskrcnn_benchmark/apex/apex/amp/rnn_compat.py
PTMD/maskrcnn_benchmark/apex/apex/amp/scaler.py
PTMD/maskrcnn_benchmark/apex/apex/amp/utils.py
PTMD/maskrcnn_benchmark/apex/apex/amp/wrap.py
PTMD/maskrcnn_benchmark/apex/apex/amp/lists/__init__.py
PTMD/maskrcnn_benchmark/apex/apex/amp/lists/functional_overrides.py
PTMD/maskrcnn_benchmark/apex/apex/amp/lists/tensor_overrides.py
PTMD/maskrcnn_benchmark/apex/apex/amp/lists/torch_overrides.py
PTMD/maskrcnn_benchmark/apex/apex/contrib/__init__.py
PTMD/maskrcnn_benchmark/apex/apex/contrib/examples/__init__.py
PTMD/maskrcnn_benchmark/apex/apex/contrib/examples/multihead_attn/__init__.py
PTMD/maskrcnn_benchmark/apex/apex/contrib/examples/multihead_attn/func_test_multihead_attn.py
PTMD/maskrcnn_benchmark/apex/apex/contrib/examples/multihead_attn/perf_test_multihead_attn.py
PTMD/maskrcnn_benchmark/apex/apex/contrib/groupbn/__init__.py
PTMD/maskrcnn_benchmark/apex/apex/contrib/groupbn/batch_norm.py
PTMD/maskrcnn_benchmark/apex/apex/contrib/multihead_attn/__init__.py
