Metadata-Version: 1.0
Name: CsuPTMD
Version: 1.0.12
Summary: word
Home-page: UNKNOWN
Author: csu_ywj
Author-email: UNKNOWN
License: MIT Licence
Keywords: pip,ptmd
Platform: any
